generate_labels/__init__.py
generate_labels/generate_labels.py
generate_labels/resources/preamble.tex
generate_labels-3.0.0.dist-info/licenses/LICENSE
generate_labels-3.0.0.dist-info/METADATA
generate_labels-3.0.0.dist-info/WHEEL
generate_labels-3.0.0.dist-info/entry_points.txt
generate_labels-3.0.0.dist-info/top_level.txt
generate_labels-3.0.0.dist-info/RECORD
