Metadata-Version: 2.4
Name: generate-labels
Version: 3.0.0
Summary: This package reads sample names from a file and arranges them on a sheet of A4 paper for printing on Avery-Zweckform L7871 labels
Author-email: Gleb Ebert <dev@gl-eb.me>
License-Expression: MIT
Requires-Python: >=3.13
License-File: LICENSE
Requires-Dist: colorama>=0.4.6
Dynamic: license-file
